{"TaskList[0].TaskModels[0].RNGSeed": "619505248", "TaskList[0].TaskModels[1].RNGSeed": "343634199", "TaskList[0].TaskModels[2].RNGSeed": "48867731", "TaskList[1].TaskModels[0].RNGSeed": "1137503348", "TaskList[1].TaskModels[1].RNGSeed": "524013213", "TaskList[1].TaskModels[2].RNGSeed": "1931020220", "TaskList[1].TaskModels[3].RNGSeed": "1059382849", "TaskList[1].TaskModels[4].RNGSeed": "157981588", "TaskList[1].TaskModels[5].RNGSeed": "583818977", "TaskList[1].TaskModels[6].RNGSeed": "514905994", "scObject.hub.sigma_BNInit": "[-0.09059658291693114,-0.031980109101998944,0.2732048672044968]", "scObject.hub.omega_BN_BInit": "[0.7768825891690102,0.028395944742624992,2.3026392206133264]"}